tomodapi/__init__.py
tomodapi/abstract_model.py
tomodapi/ctm_model.py
tomodapi/d2t_model.py
tomodapi/gensim_model.py
tomodapi/gsdmm_model.py
tomodapi/hdp_model.py
tomodapi/lda_model.py
tomodapi/lftm_model.py
tomodapi/lsi_model.py
tomodapi/nmf_model.py
tomodapi/pvtm_model.py
tomodapi/doc2topic/__init__.py
tomodapi/doc2topic/corpora.py
tomodapi/doc2topic/measures.py
tomodapi/doc2topic/models.py
tomodapi/glove/glovetokens.pkl
tomodapi/gsdmm/__init__.py
tomodapi/gsdmm/mgp.py
tomodapi/lftm/LFTM.jar
tomodapi/utils/LoggerWrapper.py
tomodapi/utils/__init__.py
tomodapi/utils/corpus.py
tomodapi-1.3.data/data/txt/requirements.txt
tomodapi-1.3.dist-info/LICENSE
tomodapi-1.3.dist-info/METADATA
tomodapi-1.3.dist-info/WHEEL
tomodapi-1.3.dist-info/top_level.txt
tomodapi-1.3.dist-info/RECORD
