Metadata-Version: 2.1
Name: tomodapi
Version: 1.3
Summary: A framework for performing topic modelling
Home-page: https://github.com/D2KLab/ToModAPI
Author: Pasquale Lisena
Author-email: pasquale.lisena@eurecom.com
License: Apache 2.0
Project-URL: Bug Tracker, https://github.com/D2KLab/tomodapi/issues/
Project-URL: Documentation, https://github.com/D2KLab/tomodapi/blob/master/README.md
Project-URL: Source Code, https://github.com/D2KLab/tomodapi/
Keywords: topic-model topic nlp
Platform: UNKNOWN
Requires-Dist: uwsgi
Requires-Dist: flask
Requires-Dist: requests
Requires-Dist: joblib
Requires-Dist: nltk
Requires-Dist: numpy
Requires-Dist: scipy (==1.4.1)
Requires-Dist: scikit-learn (==0.24.2)
Requires-Dist: gensim (==3.8.3)
Requires-Dist: tensorflow (==2.5.0)
Requires-Dist: flask-cors
Requires-Dist: flask-restx
Requires-Dist: docstring-parser
Requires-Dist: pvtm-temp
Requires-Dist: pandas
Requires-Dist: matplotlib (==3.1.3)
Requires-Dist: wordcloud
Requires-Dist: spacy
Requires-Dist: contextualized-topic-models (==2.0.1)
